[
  {
    "email": "nabeelp@microsoft.com",
    "password": "dp5z77ZS"
  },
  {
    "email": "Nagesh.Mahadev@microsoft.com",
    "password": "5zVdzfw3"
  },
  {
    "email": "Nair.Manoj@microsoft.com",
    "password": "QnGcaa88"
  },
  {
    "email": "Naomi.Alpern@microsoft.com",
    "password": "YLGtVjJZ"
  },
  {
    "email": "nashamim@microsoft.com",
    "password": "yxbGghnG"
  },
  {
    "email": "nataliak@microsoft.com",
    "password": "yWxT2Hzz"
  },
  {
    "email": "Naveed.Zaheer@microsoft.com",
    "password": "BphAKcC5"
  },
  {
    "email": "nawan@microsoft.com",
    "password": "ShNUffN5"
  },
  {
    "email": "Neel.Nanda@microsoft.com",
    "password": "eQag69pP"
  },
  {
    "email": "negupt@microsoft.com",
    "password": "vCbJE9YM"
  },
  {
    "email": "Neil.DeBrass@microsoft.com",
    "password": "nkyR6UwM"
  },
  {
    "email": "Neil.Millington@microsoft.com",
    "password": "dyyyTMSU"
  },
  {
    "email": "neimac@microsoft.com",
    "password": "zQ2QLxpA"
  },
  {
    "email": "nelsd@microsoft.com",
    "password": "U3J4D5KM"
  },
  {
    "email": "niball@microsoft.com",
    "password": "6YXt7b6R"
  },
  {
    "email": "Nicholas.Moore@microsoft.com",
    "password": "MGnB83pj"
  },
  {
    "email": "Nick.Hill@microsoft.com",
    "password": "dsTGmVJw"
  },
  {
    "email": "Nick.Hurt@microsoft.com",
    "password": "Y2SmjxRR"
  },
  {
    "email": "Nick.Powell@microsoft.com",
    "password": "sS8MtsPV"
  },
  {
    "email": "Nicolas.Barrasson@microsoft.com",
    "password": "wazTPmuE"
  },
  {
    "email": "Nicolas.Roult@microsoft.com",
    "password": "dvmYbr8F"
  },
  {
    "email": "Nicolas.Yuen@microsoft.com",
    "password": "q5hP2SNm"
  },
  {
    "email": "Nikki.Conley@microsoft.com",
    "password": "u3Q6sTuu"
  },
  {
    "email": "Nills.Franssens@microsoft.com",
    "password": "PvuF4Nx9"
  },
  {
    "email": "Ninad.Mehta@microsoft.com",
    "password": "NrjVMELE"
  },
  {
    "email": "ninad@microsoft.com",
    "password": "8zyPJcsg"
  },
  {
    "email": "Nirmal.Thewarathanthri@microsoft.com",
    "password": "z5jtA7Rj"
  },
  {
    "email": "Nitesh.Thakrar@microsoft.com",
    "password": "n62BnFBK"
  },
  {
    "email": "Nithesh.Krishnappa@microsoft.com",
    "password": "TZcXbph4"
  },
  {
    "email": "Nitin.Mehta@microsoft.com",
    "password": "zRJakz9r"
  },
  {
    "email": "Nivea.Silva@microsoft.com",
    "password": "UVdQuEsa"
  },
  {
    "email": "Norman.Sequeira@microsoft.com",
    "password": "vFhTJj9v"
  },
  {
    "email": "Nuno.Centeno@microsoft.com",
    "password": "sJfs7pXS"
  },
  {
    "email": "Nuno.Nunes@microsoft.com",
    "password": "HLE7tsq7"
  },
  {
    "email": "nusrivas@microsoft.com",
    "password": "ArPQ7n3P"
  },
  {
    "email": "nylee@microsoft.com",
    "password": "Sw5yQzEv"
  },
  {
    "email": "nzarrari@microsoft.com",
    "password": "LMynBW7n"
  },
  {
    "email": "Olavo.Borges@microsoft.com",
    "password": "FxUqxWLD"
  },
  {
    "email": "Olga.Londer@microsoft.com",
    "password": "abJkwSeB"
  },
  {
    "email": "olileger@microsoft.com",
    "password": "WwpLnZhQ"
  },
  {
    "email": "Oliver.Dorr@microsoft.com",
    "password": "3HVsRfU9"
  },
  {
    "email": "Oliver.Lohmann@microsoft.com",
    "password": "cXXVbrF3"
  },
  {
    "email": "Oliver.MulelidTynes@microsoft.com",
    "password": "nqccNsUn"
  },
  {
    "email": "Olivier.Fliche@microsoft.com",
    "password": "DCnxuXk5"
  },
  {
    "email": "Oluwasegun.Ogunbajo@microsoft.com",
    "password": "vrUHaGb2"
  },
  {
    "email": "Omkar.Naik@microsoft.com",
    "password": "RhsmfYt3"
  },
  {
    "email": "Orhan.Celik@microsoft.com",
    "password": "GnkB2hgJ"
  },
  {
    "email": "Oshik.Avioz@microsoft.com",
    "password": "HddFsRZq"
  },
  {
    "email": "Ossie.Terron@microsoft.com",
    "password": "dtDqwLk3"
  },
  {
    "email": "P.J.Grinsell@microsoft.com",
    "password": "8nsn3Jju"
  },
  {
    "email": "pabmar@microsoft.com",
    "password": "qWzZRsH3"
  },
  {
    "email": "padmar@microsoft.com",
    "password": "XsNjzX66"
  },
  {
    "email": "Param.Singh@microsoft.com",
    "password": "zFv8KkpJ"
  },
  {
    "email": "Parinaz.Bassampour@microsoft.com",
    "password": "Wh99AbGk"
  },
  {
    "email": "Park.In@microsoft.com",
    "password": "SLP3FQ63"
  },
  {
    "email": "Pascal.vanderHeiden@microsoft.com",
    "password": "qYVdQBPP"
  },
  {
    "email": "Patel.Anand@microsoft.com",
    "password": "3fx8WVAa"
  },
  {
    "email": "Patrick.Alexander@microsoft.com",
    "password": "yuk6eDQd"
  },
  {
    "email": "Patrick.Gryczka@microsoft.com",
    "password": "gyUDACwf"
  },
  {
    "email": "Patrick.vanLoon@microsoft.com",
    "password": "5ngPDXeJ"
  },
  {
    "email": "Patriek.van.Dorp@microsoft.com",
    "password": "8KWCj8Dg"
  },
  {
    "email": "Paul.Hakim@microsoft.com",
    "password": "NDsWp2Ya"
  },
  {
    "email": "Paul.Kelso@microsoft.com",
    "password": "mm5DM3Uu"
  },
  {
    "email": "paul.latham@microsoft.com",
    "password": "VjVpkDqb"
  },
  {
    "email": "Paul.Mooney@microsoft.com",
    "password": "S8Zy2Ls3"
  },
  {
    "email": "Paul.Riviera@microsoft.com",
    "password": "9n5ejhPC"
  },
  {
    "email": "Paul.Singh@microsoft.com",
    "password": "V2x26N8F"
  },
  {
    "email": "Paula.White@microsoft.com",
    "password": "9yegjUk3"
  },
  {
    "email": "Paulo.Renato@microsoft.com",
    "password": "DTU9xPRX"
  },
  {
    "email": "Pavle.Coric@microsoft.com",
    "password": "hXVdhgJr"
  },
  {
    "email": "pchiou@microsoft.com",
    "password": "bv25ChKH"
  },
  {
    "email": "pedro.martinez@microsoft.com",
    "password": "tq88qrxs"
  },
  {
    "email": "Pedro.Pereira@microsoft.com",
    "password": "vnG5RvHw"
  },
  {
    "email": "pehancoc@microsoft.com",
    "password": "5SGHDp8V"
  },
  {
    "email": "pemerker@microsoft.com",
    "password": "CAk7HtRD"
  },
  {
    "email": "pennyko@microsoft.com",
    "password": "YHBezfGW"
  },
  {
    "email": "persch@microsoft.com",
    "password": "wVSRAsJh"
  },
  {
    "email": "pete.rodriguez@microsoft.com",
    "password": "wCvCtdjn"
  },
  {
    "email": "peteb@microsoft.com",
    "password": "VGCxMyht"
  },
  {
    "email": "Peter.Beijderwellen@microsoft.com",
    "password": "mjEmWvYk"
  },
  {
    "email": "Peter.Joseph@microsoft.com",
    "password": "xTAbBKCP"
  },
  {
    "email": "Peter.Laudati@microsoft.com",
    "password": "GYZw7w7m"
  },
  {
    "email": "Peter.Liljenroth@microsoft.com",
    "password": "TESU9Aua"
  },
  {
    "email": "Peter.Lithner@microsoft.com",
    "password": "PxkuUejt"
  },
  {
    "email": "peter.souk@microsoft.com",
    "password": "7AFm5ys6"
  },
  {
    "email": "Petri.Pehkonen@microsoft.com",
    "password": "EyKKsyzM"
  },
  {
    "email": "petri.savolainen@microsoft.com",
    "password": "SMMr7jzZ"
  },
  {
    "email": "Phil.Jirsa@microsoft.com",
    "password": "S2tFPXFX"
  },
  {
    "email": "philil@microsoft.com",
    "password": "ermehNJs"
  },
  {
    "email": "Philip.Williams@microsoft.com",
    "password": "PBaPu7fe"
  },
  {
    "email": "Philipp.Loisel@microsoft.com",
    "password": "G3B7KJHr"
  },
  {
    "email": "Phillip.Marsh@microsoft.com",
    "password": "mAgmzQmm"
  },
  {
    "email": "phillipn@microsoft.com",
    "password": "eeTJyFJe"
  },
  {
    "email": "Pierre.Gagnon@microsoft.com",
    "password": "uYHJYxkp"
  },
  {
    "email": "Pierre-Olivier.Patin@microsoft.com",
    "password": "kNENqUzB"
  },
  {
    "email": "Pieter.de.Bruin@microsoft.com",
    "password": "UWCba6se"
  },
  {
    "email": "Pieter.Kestelyn@microsoft.com",
    "password": "PM26nGTS"
  },
  {
    "email": "pigilot@microsoft.com",
    "password": "GxXe82VU"
  },
  {
    "email": "Piotr.Zajac@microsoft.com",
    "password": "MnS664hg"
  },
  {
    "email": "Pleun.Nijhoff@microsoft.com",
    "password": "tWasUSEe"
  },
  {
    "email": "Prabhat.Gupta@microsoft.com",
    "password": "Dh5WGJqN"
  },
  {
    "email": "Pradeep.Kumar@microsoft.com",
    "password": "9rVeFDxW"
  },
  {
    "email": "Prakash.Beegala@microsoft.com",
    "password": "SNDYcW2S"
  },
  {
    "email": "Pranab.Paul@microsoft.com",
    "password": "mYaQMmT8"
  },
  {
    "email": "Pranav.Holavanahalli@microsoft.com",
    "password": "LEq2rCj8"
  },
  {
    "email": "Pranesh.Soundarrajan@microsoft.com",
    "password": "PVUz4SQf"
  },
  {
    "email": "prashap@microsoft.com",
    "password": "CrFU5S6t"
  },
  {
    "email": "Prateek.Gandhi@microsoft.com",
    "password": "gmVcSAwV"
  },
  {
    "email": "Pratheek.Devaraj@microsoft.com",
    "password": "qAvtZRhC"
  },
  {
    "email": "pravko@microsoft.com",
    "password": "PAzU7V5w"
  },
  {
    "email": "Prem.Samuel@microsoft.com",
    "password": "qFr5rX3P"
  },
  {
    "email": "Preston.Romney@microsoft.com",
    "password": "PbGBaZYf"
  },
  {
    "email": "Prithvi.Reddy@microsoft.com",
    "password": "GMMV6dB7"
  },
  {
    "email": "prwani@microsoft.com",
    "password": "YkRKKPAP"
  },
  {
    "email": "Pupun.Das@microsoft.com",
    "password": "ynnjYEnb"
  },
  {
    "email": "Pushker.Sahai@microsoft.com",
    "password": "wVK9uJvq"
  },
  {
    "email": "qiangzho@microsoft.com",
    "password": "c2FbenzP"
  },
  {
    "email": "Radhakrishnan.Iyer@microsoft.com",
    "password": "5FYSYBay"
  },
  {
    "email": "radut@microsoft.com",
    "password": "SuqL3NZn"
  },
  {
    "email": "Rafferty.Uy@microsoft.com",
    "password": "XzY9Rk2j"
  },
  {
    "email": "Rafik.Mazouz@microsoft.com",
    "password": "cssjKEt7"
  },
  {
    "email": "rags@microsoft.com",
    "password": "VVyW2z6c"
  },
  {
    "email": "rahgupt@microsoft.com",
    "password": "htP6zp8g"
  },
  {
    "email": "rahul.athale@microsoft.com",
    "password": "uf9yXpfB"
  },
  {
    "email": "Rahul.Deshmukh@microsoft.com",
    "password": "Tv5MNgxa"
  },
  {
    "email": "Raj.Krishnan@microsoft.com",
    "password": "ahwBDazg"
  },
  {
    "email": "Rajan.Bhayana@microsoft.com",
    "password": "SVmXr4FY"
  },
  {
    "email": "rajaque@microsoft.com",
    "password": "SZ7AYfUn"
  },
  {
    "email": "rajendran.muniappan@microsoft.com",
    "password": "FJ7Qw2hE"
  },
  {
    "email": "Rakesh.Shah@microsoft.com",
    "password": "nvzeadyX"
  },
  {
    "email": "Ralph.Kemperdick@microsoft.com",
    "password": "swUERDu5"
  },
  {
    "email": "Ram.Madhurakavi@microsoft.com",
    "password": "VM9JpEdR"
  },
  {
    "email": "Ramon.Garza@microsoft.com",
    "password": "NXZjeKGE"
  },
  {
    "email": "Raouf.Aimeur@microsoft.com",
    "password": "UvKqLdYk"
  },
  {
    "email": "rathur@microsoft.com",
    "password": "PGRdjHE8"
  },
  {
    "email": "Ravi.Kaur@microsoft.com",
    "password": "zArCzeXm"
  },
  {
    "email": "Ravi.Pedapati@microsoft.com",
    "password": "cQW8Qf6p"
  },
  {
    "email": "razkha@microsoft.com",
    "password": "jCSP4N7C"
  },
  {
    "email": "rdoherty@microsoft.com",
    "password": "an8y7VgK"
  },
  {
    "email": "Reddy.Sucharit@microsoft.com",
    "password": "JnZH55f8"
  },
  {
    "email": "Reecha.Mishra@microsoft.com",
    "password": "HsHHaMZE"
  },
  {
    "email": "Reid.Purvis@microsoft.com",
    "password": "m6EKLjjy"
  },
  {
    "email": "Rene.Hezser@microsoft.com",
    "password": "7AUWTm4p"
  },
  {
    "email": "Reuben.Cleetus@microsoft.com",
    "password": "BfADQJQz"
  },
  {
    "email": "Reza.Mahmood@microsoft.com",
    "password": "ukxCsumD"
  },
  {
    "email": "rhudson@microsoft.com",
    "password": "VYUykqjf"
  },
  {
    "email": "Ricardo.Martins@microsoft.com",
    "password": "JKWcM5m8"
  },
  {
    "email": "Ricardo.Niepel@microsoft.com",
    "password": "NVxtY5JL"
  },
  {
    "email": "Rich.McBrine@microsoft.com",
    "password": "FET3UHpt"
  },
  {
    "email": "Richard.Bannister@microsoft.com",
    "password": "N4pAxBkF"
  },
  {
    "email": "Richard.Fitzgerald@microsoft.com",
    "password": "aAc8tdH2"
  },
  {
    "email": "Richard.Hollister@microsoft.com",
    "password": "7JbRFLGZ"
  },
  {
    "email": "richard.spitz@microsoft.com",
    "password": "sJ8pNrXX"
  },
  {
    "email": "Richard.Timmering@microsoft.com",
    "password": "mRP6reVb"
  },
  {
    "email": "richjohn@microsoft.com",
    "password": "AcP2q6u8"
  },
  {
    "email": "Rick.Davis@microsoft.com",
    "password": "mjzNEfjM"
  },
  {
    "email": "rickwey@microsoft.com",
    "password": "6jSTuZrG"
  },
  {
    "email": "rifiel@microsoft.com",
    "password": "wALvMNPZ"
  },
  {
    "email": "rijen@microsoft.com",
    "password": "uUup5tes"
  },
  {
    "email": "risemaan@microsoft.com",
    "password": "m6EpzL9V"
  },
  {
    "email": "Rita.Ladda@microsoft.com",
    "password": "7zM92M7a"
  },
  {
    "email": "Ritesh.Kohli@microsoft.com",
    "password": "Fnfcezbf"
  },
  {
    "email": "Rivaaj.Jumna@microsoft.com",
    "password": "8MJtrdeh"
  },
  {
    "email": "riwasa@microsoft.com",
    "password": "kUuAEMY3"
  },
  {
    "email": "Rober.Torres@microsoft.com",
    "password": "fSBPLFS8"
  },
  {
    "email": "Robert.Biro@microsoft.com",
    "password": "7nmvCkVn"
  },
  {
    "email": "Robert.Boban@microsoft.com",
    "password": "KkKCFa7y"
  },
  {
    "email": "Robert.Turnage@microsoft.com",
    "password": "72qN9TNw"
  },
  {
    "email": "Robert.Vinod@microsoft.com",
    "password": "rLYV4czD"
  },
  {
    "email": "Robin.Ghosh@microsoft.com",
    "password": "HdmxWJwY"
  },
  {
    "email": "robnotto@microsoft.com",
    "password": "Qjk6Wkbe"
  },
  {
    "email": "Roby.Rubiano@microsoft.com",
    "password": "c5FdnY2x"
  },
  {
    "email": "Rocco.Ren@microsoft.com",
    "password": "wGQjBRvA"
  },
  {
    "email": "Rod.Means@microsoft.com",
    "password": "azuAhVN8"
  },
  {
    "email": "rodcol@microsoft.com",
    "password": "89fnDZn7"
  },
  {
    "email": "Rodrigo.Medeiros@microsoft.com",
    "password": "fnADye63"
  },
  {
    "email": "Rodrigo@microsoft.com",
    "password": "28w7GA2a"
  },
  {
    "email": "Roeland.Nieuwenhuis@microsoft.com",
    "password": "BxndgVLM"
  },
  {
    "email": "Roelf.Zomerman@microsoft.com",
    "password": "xMxfbZHu"
  },
  {
    "email": "Roger.Busser@microsoft.com",
    "password": "hekdGJuJ"
  },
  {
    "email": "rogerioc@microsoft.com",
    "password": "29afFdTy"
  },
  {
    "email": "Rolf.Tesmer@microsoft.com",
    "password": "SpahMQr5"
  },
  {
    "email": "Romain.Jauffret@microsoft.com",
    "password": "etvdeNCp"
  },
  {
    "email": "Ronald.Van.Teeffelen@microsoft.com",
    "password": "Pm7wnXbT"
  },
  {
    "email": "Rong.Fang@microsoft.com",
    "password": "hLwBeybC"
  },
  {
    "email": "Ronny.Hansen@microsoft.com",
    "password": "dVWeyDxH"
  },
  {
    "email": "rosobra@microsoft.com",
    "password": "hhmGJhxk"
  },
  {
    "email": "Roy.Prasenjit@microsoft.com",
    "password": "zeDRq7Ff"
  },
  {
    "email": "Roy.Wilson@microsoft.com",
    "password": "EhdbC4ca"
  },
  {
    "email": "royang@microsoft.com",
    "password": "jFkYzUes"
  },
  {
    "email": "Rui.Pereira@microsoft.com",
    "password": "khPeBvf2"
  },
  {
    "email": "rumor@microsoft.com",
    "password": "tpaZ7fkL"
  },
  {
    "email": "Ruqsana.Jabbar@microsoft.com",
    "password": "ZjMXm7vE"
  },
  {
    "email": "Russell.Arp@microsoft.com",
    "password": "A79mrLZK"
  },
  {
    "email": "Russell.Bradford@microsoft.com",
    "password": "J3avremu"
  },
  {
    "email": "Russell.Smith@microsoft.com",
    "password": "yQpB8ycL"
  },
  {
    "email": "Russell.Vanderpool@microsoft.com",
    "password": "v7hDNK4k"
  },
  {
    "email": "Ruth.Bacci@microsoft.com",
    "password": "sVGJnD59"
  },
  {
    "email": "Ryan.Krokson@microsoft.com",
    "password": "ZwhPZd7W"
  },
  {
    "email": "Ryan.McIntyre@microsoft.com",
    "password": "YBVawhSx"
  },
  {
    "email": "Ryan.Patch@microsoft.com",
    "password": "uH24kmr6"
  },
  {
    "email": "rygraham@microsoft.com",
    "password": "AxnXsPeW"
  },
  {
    "email": "Ryuki.Yoshimatsu@microsoft.com",
    "password": "2Ypda4tH"
  }
]
